pl_sweep/__init__.py
pl_sweep/barcode.py
pl_sweep/pl_planesweep.py
pl_sweep-0.1.0.dist-info/METADATA
pl_sweep-0.1.0.dist-info/WHEEL
pl_sweep-0.1.0.dist-info/top_level.txt
pl_sweep-0.1.0.dist-info/RECORD
