Metadata-Version: 2.1
Name: pl-sweep
Version: 0.1.0
Summary: Compute persistence landscapes using planesweep
Home-page: https://github.com/tph5595/pl-planesweep
Author: Taylor Henderson
Author-email: thender8@gmu.edu
License: MIT
Platform: UNKNOWN
Classifier: License :: OSI Approved :: MIT License
Classifier: Programming Language :: Python :: 3
Classifier: Programming Language :: Python :: 3.8
Requires-Dist: matplotlib
Requires-Dist: shapely
